mlflow_oauth_keycloak_auth/__about__.py
mlflow_oauth_keycloak_auth/__init__.py
mlflow_oauth_keycloak_auth/authentication.py
mlflow_oauth_keycloak_auth/exceptions.py
mlflow_oauth_keycloak_auth-0.0.2.post2.dist-info/METADATA
mlflow_oauth_keycloak_auth-0.0.2.post2.dist-info/WHEEL
mlflow_oauth_keycloak_auth-0.0.2.post2.dist-info/licenses/LICENCE
mlflow_oauth_keycloak_auth-0.0.2.post2.dist-info/RECORD
