Metadata-Version: 2.3
Name: mlflow-oauth-keycloak-auth
Version: 0.0.2.post2
Summary: Package for dealing with JWT tokens from Keycloak in a MLflow - oauth2-proxy setup.
Project-URL: Homepage, https://github.com/SmithyW/mlflow-oauth-keycloak-auth
Project-URL: Issues, https://github.com/SmithyW/mlflow-oauth-keycloak-auth/issues
Author-email: SmithyW <github@smiwit.de>
License-File: LICENCE
Keywords: keycloak,mlflow,oauth2
Classifier: Development Status :: 4 - Beta
Classifier: License :: OSI Approved :: MIT License
Classifier: Operating System :: OS Independent
Classifier: Programming Language :: Python :: 3
Requires-Dist: python-dotenv
Requires-Dist: requests
